CHANGES.md
LICENSE
MANIFEST.in
README.md
VERSION
requirements.txt
setup.py
django_simple_profile/__init__.py
django_simple_profile/admin.py
django_simple_profile/apps.py
django_simple_profile/models.py
django_simple_profile/urls.py
django_simple_profile/views.py
django_simple_profile.egg-info/PKG-INFO
django_simple_profile.egg-info/SOURCES.txt
django_simple_profile.egg-info/dependency_links.txt
django_simple_profile.egg-info/requires.txt
django_simple_profile.egg-info/top_level.txt
django_simple_profile/api/__init__.py
django_simple_profile/api/user_detail.py
django_simple_profile/api/user_profile.py
django_simple_profile/utils/__init__.py
django_simple_profile/utils/context_processors.py
django_simple_profile/utils/parameter.py
django_simple_profile/utils/token.py